dross/__init__.py
dross/cli.py
dross/data/__init__.py
dross/data/medallion.py
dross/models/__init__.py
dross/models/base.py
dross/models/factory.py
dross/tracking/__init__.py
dross/tracking/mlflow_tracker.py
dross/tracking/unity_catalog.py
dross/utilities/__init__.py
dross/utilities/vectorizers.py
dross-0.1.0.dist-info/METADATA
dross-0.1.0.dist-info/WHEEL
dross-0.1.0.dist-info/entry_points.txt
dross-0.1.0.dist-info/licenses/LICENSE
dross-0.1.0.dist-info/RECORD
