Metadata-Version: 2.4
Name: dross
Version: 0.1.0
Summary: ML pipeline framework: medallion architecture + MLflow + Unity Catalog
Author-email: Author <author@example.com>
License: MIT
License-File: LICENSE
Requires-Python: <3.14,>=3.12
Requires-Dist: click>=8.1
Requires-Dist: duckdb>=0.9
Requires-Dist: mlflow>=2.15
Requires-Dist: pydantic>=2.0
Requires-Dist: python-dotenv>=1.0
Requires-Dist: pyyaml>=6.0
Requires-Dist: scikit-learn>=1.3
Requires-Dist: unitycatalog-client>=0.1
